{
 "updated_epoch": 1783899174,
 "updated": "2026-07-12 19:32:54",
 "outdoor": {
  "temp_f": 77,
  "hum_pct": 56,
  "dew_f": 60.2,
  "aqi": 54,
  "pm25": 13.39,
  "wind_mph": 5,
  "wind_dir": "S"
 },
 "pool": {
  "temp_f": 83.5,
  "epoch": 1783899120
 },
 "forecast": [
  {
   "name": "Tonight",
   "temp_f": 61,
   "is_day": false,
   "precip_pct": 2,
   "short": "Mostly Clear"
  },
  {
   "name": "Monday",
   "temp_f": 86,
   "is_day": true,
   "precip_pct": 1,
   "short": "Sunny"
  }
 ],
 "rain": {
  "rate_in_hr": 0.0,
  "today_in": 0.01
 },
 "indoor": {
  "lr_temp_f": 69.6,
  "target_f": 69.0,
  "hum_pct": 68,
  "dew_f": 56.1,
  "comfort_band": "comfortable",
  "dehumidifying": false
 },
 "hvac": {
  "cool_by": "gree",
  "gree_mode": "cool",
  "gree_set_f": 62,
  "gree_fan": "high",
  "central_mode": "cool",
  "central_cool_sp_f": 69.0,
  "central_heat_sp_f": 67.7
 }
}