{
 "updated_epoch": 1784371085,
 "updated": "2026-07-18 06:38:05",
 "outdoor": {
  "temp_f": 67,
  "hum_pct": 84,
  "dew_f": 62.1,
  "aqi": 174,
  "pm25": 99.27,
  "wind_mph": 3,
  "wind_dir": "S"
 },
 "pool": {
  "temp_f": 84.7,
  "epoch": 1784371020
 },
 "forecast": [
  {
   "name": "Today",
   "temp_f": 83,
   "is_day": true,
   "precip_pct": 93,
   "short": "Smoke"
  },
  {
   "name": "Tonight",
   "temp_f": 69,
   "is_day": false,
   "precip_pct": 79,
   "short": "Showers And Thunderstorms"
  }
 ],
 "rain": {
  "rate_in_hr": 0.0,
  "today_in": 0.0
 },
 "indoor": {
  "lr_temp_f": 69.9,
  "target_f": 70.0,
  "hum_pct": 66,
  "dew_f": 57.6,
  "comfort_band": "comfortable",
  "dehumidifying": true
 },
 "hvac": {
  "cool_by": "gree",
  "gree_mode": "dry",
  "gree_set_f": 70,
  "gree_fan": "low",
  "central_mode": "off",
  "central_cool_sp_f": 68.0,
  "central_heat_sp_f": 67.7
 }
}