{
 "updated_epoch": 1784738987,
 "updated": "2026-07-22 12:49:47",
 "outdoor": {
  "temp_f": 82.4,
  "hum_pct": 56,
  "dew_f": 65.3,
  "aqi": 52,
  "pm25": 12.77,
  "wind_mph": 9,
  "wind_dir": "W"
 },
 "pool": {
  "temp_f": 83.8,
  "epoch": 1784738940
 },
 "forecast": [
  {
   "name": "Today",
   "temp_f": 84,
   "is_day": true,
   "precip_pct": 22,
   "short": "Partly Sunny then Slight Chance Showers And Thunderstorms"
  },
  {
   "name": "Tonight",
   "temp_f": 59,
   "is_day": false,
   "precip_pct": 5,
   "short": "Partly Cloudy"
  }
 ],
 "rain": {
  "rate_in_hr": 0.0,
  "today_in": 0.0
 },
 "indoor": {
  "lr_temp_f": 69.7,
  "target_f": 70.0,
  "hum_pct": 70,
  "dew_f": 56.9,
  "comfort_band": "comfortable",
  "dehumidifying": true
 },
 "hvac": {
  "cool_by": "gree",
  "gree_mode": "cool",
  "gree_set_f": 67,
  "gree_fan": "high",
  "central_mode": "cool",
  "central_cool_sp_f": 69.0,
  "central_heat_sp_f": 70.0
 }
}