{
 "updated_epoch": 1784753547,
 "updated": "2026-07-22 16:52:27",
 "outdoor": {
  "temp_f": 84.2,
  "hum_pct": 44,
  "dew_f": 60.2,
  "aqi": 36,
  "pm25": 8.77,
  "wind_mph": 10,
  "wind_dir": "W"
 },
 "pool": {
  "temp_f": 85.1,
  "epoch": 1784753520
 },
 "forecast": [
  {
   "name": "This Afternoon",
   "temp_f": 88,
   "is_day": true,
   "precip_pct": 15,
   "short": "Slight Chance Showers And Thunderstorms"
  },
  {
   "name": "Tonight",
   "temp_f": 60,
   "is_day": false,
   "precip_pct": 5,
   "short": "Partly Cloudy"
  }
 ],
 "rain": {
  "rate_in_hr": 0.0,
  "today_in": 0.0
 },
 "indoor": {
  "lr_temp_f": 70.7,
  "target_f": 70.0,
  "hum_pct": 70,
  "dew_f": 57.6,
  "comfort_band": "comfortable",
  "dehumidifying": true
 },
 "hvac": {
  "cool_by": "gree",
  "gree_mode": "cool",
  "gree_set_f": 70,
  "gree_fan": "low",
  "central_mode": "off",
  "central_cool_sp_f": 69.0,
  "central_heat_sp_f": 70.0
 }
}