{
 "updated_epoch": 1784634481,
 "updated": "2026-07-21 07:48:01",
 "outdoor": {
  "temp_f": 71,
  "hum_pct": 85,
  "dew_f": 66.2,
  "aqi": 78,
  "pm25": 25.02,
  "wind_mph": 7,
  "wind_dir": "S"
 },
 "pool": {
  "temp_f": 83.1,
  "epoch": 1784634420
 },
 "forecast": [
  {
   "name": "Today",
   "temp_f": 84,
   "is_day": true,
   "precip_pct": 73,
   "short": "Showers And Thunderstorms Likely"
  },
  {
   "name": "Tonight",
   "temp_f": 69,
   "is_day": false,
   "precip_pct": 94,
   "short": "Showers And Thunderstorms"
  }
 ],
 "rain": {
  "rate_in_hr": 0.0,
  "today_in": 0.0
 },
 "indoor": {
  "lr_temp_f": 68.4,
  "target_f": 70.0,
  "hum_pct": 68,
  "dew_f": 56.9,
  "comfort_band": "comfortable",
  "dehumidifying": false
 },
 "hvac": {
  "cool_by": "gree",
  "gree_mode": "cool",
  "gree_set_f": 69,
  "gree_fan": "med",
  "central_mode": "cool",
  "central_cool_sp_f": 71.0,
  "central_heat_sp_f": 69.0
 }
}