{
 "updated_epoch": 1784487407,
 "updated": "2026-07-19 14:56:47",
 "outdoor": {
  "temp_f": 78.8,
  "hum_pct": 43,
  "dew_f": 54.2,
  "aqi": 86,
  "pm25": 28.02,
  "wind_mph": 8,
  "wind_dir": "N"
 },
 "pool": {
  "temp_f": 85.5,
  "epoch": 1784487360
 },
 "forecast": [
  {
   "name": "This Afternoon",
   "temp_f": 83,
   "is_day": true,
   "precip_pct": 0,
   "short": "Sunny"
  },
  {
   "name": "Tonight",
   "temp_f": 57,
   "is_day": false,
   "precip_pct": 0,
   "short": "Mostly Clear"
  }
 ],
 "rain": {
  "rate_in_hr": 0.0,
  "today_in": 0.12
 },
 "indoor": {
  "lr_temp_f": 68.8,
  "target_f": 70.0,
  "hum_pct": 68,
  "dew_f": 55.0,
  "comfort_band": "comfortable",
  "dehumidifying": false
 },
 "hvac": {
  "cool_by": "gree",
  "gree_mode": "cool",
  "gree_set_f": 63,
  "gree_fan": "high",
  "central_mode": "cool",
  "central_cool_sp_f": 69.0,
  "central_heat_sp_f": 69.0
 }
}